simplesockets/__init__.py
simplesockets/secure_sockets.py
simplesockets/simple_sockets.py
simplesockets/typehints.py
simplesockets/_support_files/Events.py
simplesockets/_support_files/RSA.py
simplesockets/_support_files/__init__.py
simplesockets/_support_files/b_veginer.py
simplesockets/_support_files/cipher.py
simplesockets/_support_files/colum_transposition.py
simplesockets/_support_files/error.py
simplesockets/_support_files/primes.py
simplesockets/example/__init__.py
simplesockets/example/echo_client.py
simplesockets/example/echo_server.py
simplesockets/securesockets/PyCryptodome_Socket.py
simplesockets/securesockets/SelfmadeCipher_Socket.py
simplesockets/securesockets/__init__.py
tests/__init__.py
tests/test_PyCryptodome_Socket.py
tests/test_SelfmadeCipher_Socket.py
tests/test_secure_sockets.py
tests/test_simple_sockets.py
simplesockets-0.4.0.dist-info/LICENSE
simplesockets-0.4.0.dist-info/METADATA
simplesockets-0.4.0.dist-info/WHEEL
simplesockets-0.4.0.dist-info/top_level.txt
simplesockets-0.4.0.dist-info/RECORD
