Metadata-Version: 2.1
Name: simplesockets
Version: 0.4.0
Summary: Allows the use of python sockets more easily
Home-page: https://github.com/MrPoisen/simplesockets
Author: MrPoisen
License: UNKNOWN
Project-URL: Bug Tracker, https://github.com/MrPoisen/simplesockets/issues
Project-URL: Feature Requests, https://github.com/MrPoisen/simplesockets/issues
Project-URL: Documentation, https://mrpoisen.github.io/simplesockets/
Platform: UNKNOWN
Classifier: Programming Language :: Python :: 3
Classifier: License :: OSI Approved :: GNU General Public License v3 (GPLv3)
Classifier: Operating System :: Microsoft :: Windows
Classifier: Development Status :: 4 - Beta
Classifier: Intended Audience :: Developers
Requires-Python: >=3.6
License-File: LICENSE
